shuffl/__init__.py
shuffl/analyze.py
shuffl/deck.py
shuffl/exceptions.py
shuffl/models.py
shuffl/simulate.py
shuffl-0.1.0.dist-info/LICENSE
shuffl-0.1.0.dist-info/METADATA
shuffl-0.1.0.dist-info/WHEEL
shuffl-0.1.0.dist-info/RECORD
