Metadata-Version: 2.1
Name: shuffl
Version: 0.1.0
Summary: 
Author: jmssnr
Author-email: maussner.johannes@gmail.com
Requires-Python: >=3.11,<4.0
Classifier: Programming Language :: Python :: 3
Classifier: Programming Language :: Python :: 3.11
Classifier: Programming Language :: Python :: 3.12
Requires-Dist: numpy (>=1.26.3,<2.0.0)
